aws_recommendation_a6/__init__.py
aws_recommendation_a6/cloudwatch.py
aws_recommendation_a6/cost_estimations.py
aws_recommendation_a6/dynamodb.py
aws_recommendation_a6/ebs.py
aws_recommendation_a6/ec2.py
aws_recommendation_a6/elb.py
aws_recommendation_a6/kms.py
aws_recommendation_a6/rds.py
aws_recommendation_a6/recommendation.py
aws_recommendation_a6/redshift.py
aws_recommendation_a6/s3.py
aws_recommendation_a6/truted_advisor.py
aws_recommendation_a6/utils.py
aws_recommendation_a6-0.0.18.dist-info/LICENCE
aws_recommendation_a6-0.0.18.dist-info/METADATA
aws_recommendation_a6-0.0.18.dist-info/WHEEL
aws_recommendation_a6-0.0.18.dist-info/top_level.txt
aws_recommendation_a6-0.0.18.dist-info/RECORD
